{
    "general": {
        "name": "Comfy",
        "home": "Domů",
        "all": "Procházet",
        "settings": "Nastavení",
        "download": "Stažení",
        "login": "Přihlásit se"
    },
    "home": {
        "favourites": "Oblíbené",
        "airing": "Sezonní série",
        "soon": "Plánované epizody",
        "latest": "Nové epizody",
        "random": "Náhodné série",
        "releasedAgo": "před {{time}}",
        "releasedAgoWaiting": "před {{time}}",
        "releaseIn": "za {{time}}"
    },
    "footer": {
        "hosting": "Hostuje se {{files}} souborů o velikosti {{size}}"
    },
    "all": {
        "title": "Série ({{count}}):",
        "genres": "Žánr: {{genre}}",
        "year": "Rok: {{year}}",
        "type": "Typ: {{type}}",
        "status": "Status: {{status}}",
        "sort": "Pořadí: {{sort}}",
        "tags": "Tag: {{tags}}",
        "search": "Vyhledat...",
        "items": "Položek: {{items}}",
        "group": "Seskupit: {{group}}"
    },
    "filter": {
        "default": "Výchozí",
        "any": "Jakýkoliv"
    },
    "genre": {
        "any": "Jakýkoliv"
    },
    "enum": {
        "preferencesTheme": {
            "0": "Tmavý",
            "1": "Světlý"
        },
        "notificationPreference": {
            "default": "Vypnuty",
            "granted": "Zapnuty",
            "denied": "Zablokovány",
            "notLoggedIn": "Nepřihlášen",
            "off": "Vypnuty"
        },
        "authResult": {
            "NONE": "",
            "USERNAME_TOO_SHORT": "Uživatelské jméno je moc krátké!",
            "PASSWORD_TOO_SHORT": "Heslo je moc krátké!",
            "PASSWORD_NO_MATCH": "Hesla se neshodují!",
            "NOT_FOUND": "Nepodařilo se přihlásit!",
            "NOT_AUTHORIZED": "Nepodařilo se přihlásit!",
            "USER_TAKEN": "Uživatel už existuje!"
        },
        "filterType": {
            "0": "Žánry",
            "1": "Rok",
            "2": "Typ",
            "3": "Status",
            "4": "Řazení",
            "5": "Tagy",
            "6": "Položky",
            "7": "Skupiny"
        },
        "filterSort": {
            "0": "Název (A-Z)",
            "1": "Název (Z-A)",
            "2": "Datum (Nové)",
            "3": "Datum (Staré)",
            "4": "Hvězdičky (Nejvíce)",
            "5": "Hvězdičky (Nejméně)"
        },
        "filterGroup": {
            "0": "Ano",
            "1": "Ne"
        },
        "showType": {
            "0": "TV",
            "1": "Speciál",
            "2": "OVA",
            "3": "Film",
            "4": "ONA"
        },
        "showStatus": {
            "0": "Vysíláno",
            "1": "Dokončeno"
        },
        "showGenre": {
            "1": "Akce",
            "2": "Dobrodružství",
            "4": "Komedie",
            "8": "Drama",
            "16": "Ecchi",
            "32": "Fantazie",
            "64": "Horror",
            "128": "Mahou Shoujo",
            "256": "Mecha",
            "512": "Hudba",
            "1024": "Záhada",
            "2048": "Psychologické",
            "4096": "Romantické",
            "8192": "Sci-Fi",
            "16384": "Denní život",
            "32768": "Sport",
            "65536": "Supernaturální",
            "131072": "Thriller"
        },
        "showTag": {
            "1": "Titulky",
            "2": "Stálé titulky",
            "4": "Dabovaný"
        },
        "showRating": {
            "0": "PG",
            "1": "R"
        },
        "segmentType": {
            "0": "OP",
            "1": "Epizoda",
            "2": "ED"
        },
        "videoPlayerNotification": {
            "OP": "Přeskočit intro?",
            "ED": "Přeskočit outro?"
        }
    },
    "settings": {
        "theme": "Vzhled: {{theme}}",
        "notifications": "Notifikace: {{status}}"
    },
    "show": {
        "favourite": {
            "tooltip": {
                "notLoggedIn": "Přihlašte se pro tuto funkci",
                "false": "Přidat do oblíbených",
                "true": "Odebrat z oblíbených"
            }
        },
        "type": "Typ: ",
        "status": "Status: ",
        "genres": "Žánry: ",
        "episodes": "Počet epizod: ",
        "favourites": "Hvězdičky: ",
        "views": "Počet zhlédnutí: ",
        "tags": "Tagy: ",
        "missing": "Tady nic",
        "episode": {
            "number": "Epizoda {{num}}/{{episodes}}",
            "play": "Přehrát",
            "download": "Stáhnout",
            "missing": "Tady nic"
        },
        "noTags": "Žádné",
        "noGenres": "Žádné",
        "noSynopsis": "Žádná synopse..."
    },
    "episode": {
        "number": "Epizoda {{num}} - ",
        "show": "Série: "
    },
    "download": {
        "title": "Stažení",
        "link": "Stáhnout"
    },
    "group": {
        "seasons": "{{count}} sezón",
        "season": "Sezóna {{number}}"
    },
    "login": {
        "title": "Přihlášení",
        "button": "Přihlásit se",
        "username": {
            "placeholder": "Uživatelské jméno..."
        },
        "password": {
            "placeholder": "Heslo..."
        },
        "noAccount": "Žádný účet? (Zaregistrovat se)"
    },
    "register": {
        "title": "Registace",
        "button": "Registrovat se",
        "username": {
            "placeholder": "Uživatelské jméno..."
        },
        "password": {
            "placeholder": "Heslo..."
        },
        "password_2": {
            "placeholder": "Heslo znovu..."
        },
        "existingAccount": "Existující účet? (Přihlásit se)"
    },
    "video": {
        "play": {
            "tooltip": "Přehrát (k)"
        },
        "pause": {
            "tooltip": "Pozastavit (k)"
        },
        "unmute": {
            "tooltip": "Odtlumit (m)"
        },
        "mute": {
            "tooltip": "Tlumit (m)"
        },
        "volume": "Hlasitost ({{volume}}%)",
        "showSubtitles": {
            "tooltip": "Zobrazit titulky (c)"
        },
        "hideSubtitles": {
            "tooltip": "Skrýt titulky (c)"
        },
        "noDub": "Není dabováno",
        "quality": "Kvalita - {{quality}} ({{number}}/{{count}})",
        "showTheater": {
            "tooltip": "Režim divalda (t)"
        },
        "hideTheater": {
            "tooltip": "Režim divalda (t)"
        },
        "fullscreen": {
            "tooltip": "Celá obrazovka (f)"
        },
        "notification": {
            "skip": "Přeskočit",
            "hide": "Skrýt"
        }
    }
}